adbdevicechanger/LICENSE
adbdevicechanger/README.MD
adbdevicechanger/__init__.py
adbdevicechanger/requirements.txt
adbdevicechanger/thirdparty.json
adbdevicechanger-0.11.dist-info/LICENSE.rst
adbdevicechanger-0.11.dist-info/METADATA
adbdevicechanger-0.11.dist-info/WHEEL
adbdevicechanger-0.11.dist-info/top_level.txt
adbdevicechanger-0.11.dist-info/RECORD
